invenio_utilities_tuw/__init__.py
invenio_utilities_tuw/config.py
invenio_utilities_tuw/ext.py
invenio_utilities_tuw/utils.py
invenio_utilities_tuw/cli/__init__.py
invenio_utilities_tuw/cli/cli.py
invenio_utilities_tuw/cli/drafts.py
invenio_utilities_tuw/cli/files.py
invenio_utilities_tuw/cli/notifications.py
invenio_utilities_tuw/cli/options.py
invenio_utilities_tuw/cli/records.py
invenio_utilities_tuw/cli/reports.py
invenio_utilities_tuw/cli/users.py
invenio_utilities_tuw/cli/utils.py
invenio_utilities_tuw/cli/vocabularies.py
invenio_utilities_tuw-2025.1.3.dist-info/METADATA
invenio_utilities_tuw-2025.1.3.dist-info/WHEEL
invenio_utilities_tuw-2025.1.3.dist-info/entry_points.txt
invenio_utilities_tuw-2025.1.3.dist-info/licenses/AUTHORS.rst
invenio_utilities_tuw-2025.1.3.dist-info/licenses/LICENSE
invenio_utilities_tuw-2025.1.3.dist-info/RECORD
