Metadata-Version: 2.4
Name: Invenio-Utilities-tuw
Version: 2025.1.3
Summary: Some utilities for InvenioRDM.
Project-URL: Repository, https://gitlab.tuwien.ac.at/fairdata/invenio-utilities-tuw
Author-email: "Team of the Center for Research Data Management (TU Wien)" <tudata@tuwien.ac.at>
License-Expression: MIT
License-File: AUTHORS.rst
License-File: LICENSE
Keywords: cli,invenio,tu wien,utilities
Classifier: Development Status :: 5 - Production/Stable
Classifier: Environment :: Web Environment
Classifier: License :: OSI Approved :: MIT License
Classifier: Operating System :: OS Independent
Classifier: Programming Language :: Python
Classifier: Programming Language :: Python :: 3.12
Classifier: Programming Language :: Python :: 3.13
Classifier: Topic :: Internet :: WWW/HTTP :: Dynamic Content
Classifier: Topic :: Software Development :: Libraries :: Python Modules
Requires-Python: >=3.12
Requires-Dist: invenio-app-rdm>=12.0.0
Provides-Extra: tests
Requires-Dist: invenio-search[opensearch2]>=2.0.0; extra == 'tests'
Requires-Dist: pytest-black<0.3.10,>=0.3.0; extra == 'tests'
Requires-Dist: pytest-invenio>=1.4.0; extra == 'tests'
Requires-Dist: pytest-ruff>=0.4.1; extra == 'tests'
Requires-Dist: sphinx>=4.5; extra == 'tests'
